{
//回家地址 → https://www.avbook.cc/
//https://www.sftv.in/
//免翻线路跳转mmgy.net/mmgy.pw/mmgy.de/hd7000.com/javbus.run
"规则名": "私房TV-XYQHiker",
"规则作者": "飞鱼",
"请求头参数": "手机",
"网页编码格式": "UTF-8",
"图片是否需要代理": "0",
"是否开启获取首页数据": "1",
"首页推荐链接": "https://jky.202mm.cc",
"首页列表数组规则": ".videos-list",
"首页片单列表数组规则": "article",
"首页片单是否Jsoup写法": "1",
"首页片单标题": ".entry-header&&Text",
"首页片单链接": "a&&href",
"首页片单图片": "img&&data-src",
"首页片单副标题": "'⏱️'+span,1&&Text+'👁️'+.views&&Text",
"首页片单链接加前缀": "https://jky.202mm.cc",
"首页片单链接加后缀": "",
"分类起始页码": "1",
"分类链接": "https://jky.202mm.cc/{cateId}/page/{catePg}.html",
"分类名称": "偷拍自拍&91视频合集&黑料吃瓜&国产AV&网红福利&女优/无码&更多分类",
"分类名称替换词": "vodtype/23&vodtype/30&vodtype/28&vodtype/27&vodtype/31&vodtype/26&91pron-77",
"分类截取模式": "1",
"分类列表数组规则": ".videos-list&&article",
"分类片单是否Jsoup写法": "1",
"分类片单标题": ".entry-header&&Text",
"分类片单链接": "a&&href",
"分类片单图片": "img&&data-src",
"分类片单副标题": "'⏱️'+span,1&&Text+'👁️'+.views&&Text",

"分类片单链接加前缀": "https://jky.202mm.cc",
"分类片单链接加后缀": "",
"搜索请求头参数": "User-Agent$PC_UA",
"搜索链接": "https://jky.202mm.cc/index.php/ajax/suggest?mid=1&wd={wd}",
"POST请求数据": "",
"搜索截取模式": "0",
"搜索列表数组规则": "list",
"搜索片单是否Jsoup写法": "1",
"搜索片单图片": "pic",
"搜索片单标题": "name",
"搜索片单链接": "id",
"搜索片单副标题": "",
"搜索片单链接加前缀": "https://jky.202mm.cc/v/",
"搜索片单链接加后缀": "-1-1.html",
"链接是否直接播放": "1",
"直接播放链接加前缀": "",
"直接播放链接加后缀": "",
"直接播放直链视频请求头": "",
 "详情是否Jsoup写法":"0",
    "类型详情": "<p>類型：&&</p>",
    "年代详情": "<p>更新：&&</p>",
    "地区详情": "",
    "演员详情": "",
    "简介详情": "",
    "线路列表数组规则": ".play-btn-group&&.line",
    "线路标题": "'📽️'+a&&Text+'📺'",
    "播放列表数组规则": ".line",
    "选集列表数组规则": "a",
    "选集标题链接是否Jsoup写法":"1",
    "选集标题": "a&&Text",
    "选集链接": "a&&href",
    "是否反转选集序列": "0",
    "选集链接加前缀": "https://jky.202mm.cc",
    "选集链接加后缀": "",
   
"筛选数据":{
"91pron-77":[
  {"key":"cateId",
  "name":"分类",
  "value":[
{"v":"91pron-77","n":"女仆"}, 
{"v":"91pron-105","n":"熟女"}, 
{"v":"91pron-68","n":"良家"}, 
{"v":"91pron-70","n":"模特"}, 
{"v":"91pron-103","n":"反差婊"}, 
{"v":"91pron-66","n":"双飞"}, 
{"v":"91pron-110","n":"人妻"}, 
{"v":"91pron-112","n":"丝袜"}, 
{"v":"91pron-101","n":"秀人网"}, 
{"v":"91pron-109","n":"乱伦"}, 
{"v":"91pron-124","n":"口交"}, 
{"v":"91pron-111","n":"巨乳大奶"}, 
{"v":"91pron-58","n":"萝莉"}, 
{"v":"91pron-71","n":"按摩spa"}, 
{"v":"91pron-102","n":"偷拍"}, 
{"v":"91pron-69","n":"学生"}, 
{"v":"91pron-108","n":"会所ktv"}, 
{"v":"91pron-61","n":"女神"}, 
{"v":"91pron-33","n":"空姐"}, 
{"v":"91pron-80","n":"91pron自拍,91大神合集"}, 
{"v":"91pron-65","n":"3p"}, 
{"v":"91pron-121","n":"91猫先生"}, 
{"v":"91pron-123","n":"福利姬"}, 
{"v":"91pron-94","n":"三上悠亚"}, 
{"v":"91pron-95","n":"相泽南"}, 
{"v":"91pron-100","n":"星宫一花"}, 
{"v":"91pron-99","n":"桥本有菜"}, 
{"v":"91pron-98","n":"石川澪"}, 
{"v":"91pron-97","n":"明里䌷"}, 
{"v":"91pron-96","n":"桃乃木香奈"}, 
{"v":"91pron-92","n":"杨晨晨"}, 
{"v":"91pron-113","n":"调教"}, 
{"v":"91pron-104","n":"韩国色情"}, 
{"v":"91pron-114","n":"后入"}, 
{"v":"91pron-107","n":"Ai明星换脸"}, 
{"v":"91pron-93","n":"自慰"}, 
{"v":"91pron-122","n":"麻豆兔子先生"}, 
{"v":"91pron-120","n":"91秦先生"}, 
{"v":"91pron-119","n":"91康先生"}, 
{"v":"91pron-118","n":"91夯先生"}, 
{"v":"91pron-117","n":"91风吟鸟唱"}, 
{"v":"91pron-116","n":"91大神CAT3500"}, 
{"v":"91pron-115","n":"91大神91xh98hx"}, 
{"v":"91pron-64","n":"七天高端外围"}, 
{"v":"91pron-52","n":"探花郎李寻欢"}, 
{"v":"91pron-36","n":"小宝探花"}, 
{"v":"91pron-60","n":"利哥探花"}, 
{"v":"91pron-106","n":"探花"}, 
{"v":"91pron-35","n":"91沈先生"}, 
{"v":"91pron-39","n":"鸭哥探花"}, 
{"v":"91pron-44","n":"小陈头星选"}, 
{"v":"91pron-48","n":"小马探花"}, 
{"v":"91pron-49","n":"文轩探花"}, 
{"v":"91pron-74","n":"步宾探花"}, 
{"v":"91pron-75","n":"赵总探花"}, 
{"v":"91pron-76","n":"专找老阿姨"}]}
],
"/vodshow/2":[
  {"key":"cateId",
  "name":"分类",
  "value":[
{"v":"/vodshow/2","n":"全部"},
{"v":"/vodshow/13","n":"日本无码"},
{"v":"/vodshow/14","n":"中文字幕"},
{"v":"/vodshow/15","n":"日韩有码"},
{"v":"/vodshow/16","n":"AV解说"}]},
{"key":"by",
  "name":"排序",
  "value":[
  {"v":"","n":"最新"},
  {"v":"hits","n":"热门"},
  {"v":"up","n":"点赞"},
  {"v":"score","n":"评分"}
]}
],
"/vodshow/21":[
{"key":"by",
  "name":"排序",
  "value":[
  {"v":"","n":"最新"},
  {"v":"hits","n":"热门"},
  {"v":"up","n":"点赞"},
  {"v":"score","n":"评分"}
]}
],
"/vodshow/3":[
{"key":"by",
  "name":"排序",
  "value":[
  {"v":"","n":"最新"},
  {"v":"hits","n":"热门"},
  {"v":"up","n":"点赞"},
  {"v":"score","n":"评分"}
]}
],
"/vodshow/4":[
{"key":"by",
  "name":"排序",
  "value":[
  {"v":"","n":"最新"},
  {"v":"hits","n":"热门"},
  {"v":"up","n":"点赞"},
  {"v":"score","n":"评分"}
]}
],
"/vodshow/5":[
{"key":"by",
  "name":"排序",
  "value":[
  {"v":"","n":"最新"},
  {"v":"hits","n":"热门"},
  {"v":"up","n":"点赞"},
  {"v":"score","n":"评分"}
]}
],
"/vodshow/20":[
{"key":"by",
  "name":"排序",
  "value":[
  {"v":"","n":"最新"},
  {"v":"hits","n":"热门"},
  {"v":"up","n":"点赞"},
  {"v":"score","n":"评分"}
]}
],
"/vodshow/22":[
{"key":"by",
  "name":"排序",
  "value":[
  {"v":"","n":"最新"},
  {"v":"hits","n":"热门"},
  {"v":"up","n":"点赞"},
  {"v":"score","n":"评分"}
]}
]


},

"分析MacPlayer": "0",
"是否开启手动嗅探": "1",
"手动嗅探视频链接关键词": ".m3u8#.mp4",
"手动嗅探视频链接过滤词": "baidu.com"
}